{
  "hash": "b042a1ec842620984e4fa1b129509168",
  "result": {
    "markdown": "---\ntitle: \"Mercado Mayorista - MOVISTAR\"\nformat: html\neditor: visual\n---\n\n\n#### MOVISTAR\nLos cargos IoT de la empresa MOVISTAR (OTECEL S.A.) con operadoras de Chile se realizan a través de la negociación entre las partes. Para llamadas saliente origen como llamadas locales, SMS y datos móviles **los cargos mayoristas negociados entre operadoras son recíprocos**.\n\n\n##### Tarifas mayoristas de Movistar Ecuador (Outbound y Inbound)\n\n\n\n::: {.cell}\n::: {.cell-output-display}\n```{=html}\n<div class=\"datatables html-widget html-fill-item-overflow-hidden html-fill-item\" id=\"htmlwidget-deb808c2b2e8aa5a4290\" style=\"width:100%;height:auto;\"></div>\n<script type=\"application/json\" data-for=\"htmlwidget-deb808c2b2e8aa5a4290\">{\"x\":{\"filter\":\"none\",\"vertical\":false,\"data\":[[\"1\",\"2\",\"3\",\"4\",\"5\",\"6\"],[\"Claro\",\"Movistar\",\"Movistar\",\"Entel\",\"Wom\",\"Wom\"],[0.0018,0.001,0.001,0.0018,0.0042,0.0025],[0.0018,0.001,0.001,0.0018,0.0042,0.0025],[0.0058,0.0025,0.0025,0.0042,0.0083,0.0042],[0.005,0.005,0.012,0.008999999999999999,0.05,0.01],[0,0,0,0,0.0001,0],[\"Oct 2020 – Actual\",\"Ene 2020 – Dic 2022\",\"Ene 2023 – Actual\",\"May 2021 – Actual\",\"May 2022 – Nov 2023\",\"Dic 2023 – Actual\"]],\"container\":\"<table class=\\\"display\\\">\\n  <thead>\\n    <tr>\\n      <th> <\\/th>\\n      <th>Operador<\\/th>\\n      <th>Llamada Saliente \\r\\nLocal<\\/th>\\n      <th>Llamada \\r\\nSaliente \\r\\nOrigen<\\/th>\\n      <th>Llamada \\r\\nSaliente \\r\\n Internacional<\\/th>\\n      <th>SMS<\\/th>\\n      <th>Datos \\r\\n(MB)<\\/th>\\n      <th>Vigencia<\\/th>\\n    <\\/tr>\\n  <\\/thead>\\n<\\/table>\",\"options\":{\"columnDefs\":[{\"className\":\"dt-right\",\"targets\":[2,3,4,5,6]},{\"orderable\":false,\"targets\":0}],\"order\":[],\"autoWidth\":false,\"orderClasses\":false}},\"evals\":[],\"jsHooks\":[]}</script>\n```\n:::\n:::\n\n\n\nAdicionalmente se analiza el tráfico outbound versus el tráfico inbound en el periodo analizado, obteniéndose una relación positiva en los diferentes servicios:\n- La relación de tráfico de Voz Saliente inbound vs outbound es igual a 7.07.\n- La relación de tráfico SMS inbound vs outbound es igual a 10.89.\n- La relación de tráfico de Datos móviles inboudn vs outbound es igual a 3.1022.\n\n\n::: {.cell}\n::: {.cell-output-display}\n```{=html}\n<div class=\"highchart html-widget html-fill-item-overflow-hidden html-fill-item\" id=\"htmlwidget-f32e3aa3e4fd995ba5c1\" style=\"width:100%;height:464px;\"></div>\n<script type=\"application/json\" data-for=\"htmlwidget-f32e3aa3e4fd995ba5c1\">{\"x\":{\"hc_opts\":{\"chart\":{\"reflow\":true},\"title\":{\"text\":\"<b>Tráfico Voz Movistar Roaming Chile-Ecuador<\\/b>\"},\"yAxis\":{\"title\":{\"text\":\"tráfico_voz\"},\"type\":\"linear\"},\"credits\":{\"enabled\":false,\"enable\":true,\"text\":\"https://github.com/raulavilesrodriguez\"},\"exporting\":{\"enabled\":false},\"boost\":{\"enabled\":false},\"plotOptions\":{\"series\":{\"label\":{\"enabled\":false},\"turboThreshold\":0,\"showInLegend\":true},\"treemap\":{\"layoutAlgorithm\":\"squarified\"},\"scatter\":{\"marker\":{\"symbol\":\"circle\"}}},\"series\":[{\"name\":\"VOZ TOTAL TRAFICO Inbound\",\"data\":[{\"Fecha\":\"2022-01-01\",\"tipo\":\"VOZ TOTAL TRAFICO Inbound\",\"tráfico_voz\":5005,\"x\":1640995200000,\"y\":5005},{\"Fecha\":\"2022-02-01\",\"tipo\":\"VOZ TOTAL TRAFICO Inbound\",\"tráfico_voz\":2636,\"x\":1643673600000,\"y\":2636},{\"Fecha\":\"2022-03-01\",\"tipo\":\"VOZ TOTAL TRAFICO Inbound\",\"tráfico_voz\":3397,\"x\":1646092800000,\"y\":3397},{\"Fecha\":\"2022-04-01\",\"tipo\":\"VOZ TOTAL TRAFICO Inbound\",\"tráfico_voz\":3568,\"x\":1648771200000,\"y\":3568},{\"Fecha\":\"2022-05-01\",\"tipo\":\"VOZ TOTAL TRAFICO Inbound\",\"tráfico_voz\":3575,\"x\":1651363200000,\"y\":3575},{\"Fecha\":\"2022-06-01\",\"tipo\":\"VOZ TOTAL TRAFICO Inbound\",\"tráfico_voz\":2388,\"x\":1654041600000,\"y\":2388},{\"Fecha\":\"2022-07-01\",\"tipo\":\"VOZ TOTAL TRAFICO Inbound\",\"tráfico_voz\":3317,\"x\":1656633600000,\"y\":3317},{\"Fecha\":\"2022-08-01\",\"tipo\":\"VOZ TOTAL TRAFICO Inbound\",\"tráfico_voz\":4226,\"x\":1659312000000,\"y\":4226},{\"Fecha\":\"2022-09-01\",\"tipo\":\"VOZ TOTAL TRAFICO Inbound\",\"tráfico_voz\":2392,\"x\":1661990400000,\"y\":2392},{\"Fecha\":\"2022-10-01\",\"tipo\":\"VOZ TOTAL TRAFICO Inbound\",\"tráfico_voz\":2677,\"x\":1664582400000,\"y\":2677},{\"Fecha\":\"2022-11-01\",\"tipo\":\"VOZ TOTAL TRAFICO Inbound\",\"tráfico_voz\":3657,\"x\":1667260800000,\"y\":3657},{\"Fecha\":\"2022-12-01\",\"tipo\":\"VOZ TOTAL TRAFICO Inbound\",\"tráfico_voz\":4268,\"x\":1669852800000,\"y\":4268},{\"Fecha\":\"2023-01-01\",\"tipo\":\"VOZ TOTAL TRAFICO Inbound\",\"tráfico_voz\":5309,\"x\":1672531200000,\"y\":5309},{\"Fecha\":\"2023-02-01\",\"tipo\":\"VOZ TOTAL TRAFICO Inbound\",\"tráfico_voz\":6043,\"x\":1675209600000,\"y\":6043},{\"Fecha\":\"2023-03-01\",\"tipo\":\"VOZ TOTAL TRAFICO Inbound\",\"tráfico_voz\":6000,\"x\":1677628800000,\"y\":6000},{\"Fecha\":\"2023-04-01\",\"tipo\":\"VOZ TOTAL TRAFICO Inbound\",\"tráfico_voz\":4293,\"x\":1680307200000,\"y\":4293},{\"Fecha\":\"2023-05-01\",\"tipo\":\"VOZ TOTAL TRAFICO Inbound\",\"tráfico_voz\":3502,\"x\":1682899200000,\"y\":3502},{\"Fecha\":\"2023-06-01\",\"tipo\":\"VOZ TOTAL TRAFICO Inbound\",\"tráfico_voz\":3926,\"x\":1685577600000,\"y\":3926},{\"Fecha\":\"2023-07-01\",\"tipo\":\"VOZ TOTAL TRAFICO Inbound\",\"tráfico_voz\":3945,\"x\":1688169600000,\"y\":3945},{\"Fecha\":\"2023-08-01\",\"tipo\":\"VOZ TOTAL TRAFICO Inbound\",\"tráfico_voz\":5289,\"x\":1690848000000,\"y\":5289},{\"Fecha\":\"2023-09-01\",\"tipo\":\"VOZ TOTAL TRAFICO Inbound\",\"tráfico_voz\":3621,\"x\":1693526400000,\"y\":3621}],\"type\":\"line\"},{\"name\":\"VOZ TOTAL TRAFICO Outbound\",\"data\":[{\"Fecha\":\"2022-01-01\",\"tipo\":\"VOZ TOTAL TRAFICO Outbound\",\"tráfico_voz\":458,\"x\":1640995200000,\"y\":458},{\"Fecha\":\"2022-02-01\",\"tipo\":\"VOZ TOTAL TRAFICO Outbound\",\"tráfico_voz\":396,\"x\":1643673600000,\"y\":396},{\"Fecha\":\"2022-03-01\",\"tipo\":\"VOZ TOTAL TRAFICO Outbound\",\"tráfico_voz\":732,\"x\":1646092800000,\"y\":732},{\"Fecha\":\"2022-04-01\",\"tipo\":\"VOZ TOTAL TRAFICO Outbound\",\"tráfico_voz\":784,\"x\":1648771200000,\"y\":784},{\"Fecha\":\"2022-05-01\",\"tipo\":\"VOZ TOTAL TRAFICO Outbound\",\"tráfico_voz\":592,\"x\":1651363200000,\"y\":592},{\"Fecha\":\"2022-06-01\",\"tipo\":\"VOZ TOTAL TRAFICO Outbound\",\"tráfico_voz\":703,\"x\":1654041600000,\"y\":703},{\"Fecha\":\"2022-07-01\",\"tipo\":\"VOZ TOTAL TRAFICO Outbound\",\"tráfico_voz\":435,\"x\":1656633600000,\"y\":435},{\"Fecha\":\"2022-08-01\",\"tipo\":\"VOZ TOTAL TRAFICO Outbound\",\"tráfico_voz\":867,\"x\":1659312000000,\"y\":867},{\"Fecha\":\"2022-09-01\",\"tipo\":\"VOZ TOTAL TRAFICO Outbound\",\"tráfico_voz\":177,\"x\":1661990400000,\"y\":177},{\"Fecha\":\"2022-10-01\",\"tipo\":\"VOZ TOTAL TRAFICO Outbound\",\"tráfico_voz\":711,\"x\":1664582400000,\"y\":711},{\"Fecha\":\"2022-11-01\",\"tipo\":\"VOZ TOTAL TRAFICO Outbound\",\"tráfico_voz\":1010,\"x\":1667260800000,\"y\":1010},{\"Fecha\":\"2022-12-01\",\"tipo\":\"VOZ TOTAL TRAFICO Outbound\",\"tráfico_voz\":1331,\"x\":1669852800000,\"y\":1331},{\"Fecha\":\"2023-01-01\",\"tipo\":\"VOZ TOTAL TRAFICO Outbound\",\"tráfico_voz\":709,\"x\":1672531200000,\"y\":709},{\"Fecha\":\"2023-02-01\",\"tipo\":\"VOZ TOTAL TRAFICO Outbound\",\"tráfico_voz\":531,\"x\":1675209600000,\"y\":531},{\"Fecha\":\"2023-03-01\",\"tipo\":\"VOZ TOTAL TRAFICO Outbound\",\"tráfico_voz\":640,\"x\":1677628800000,\"y\":640},{\"Fecha\":\"2023-04-01\",\"tipo\":\"VOZ TOTAL TRAFICO Outbound\",\"tráfico_voz\":523,\"x\":1680307200000,\"y\":523},{\"Fecha\":\"2023-05-01\",\"tipo\":\"VOZ TOTAL TRAFICO Outbound\",\"tráfico_voz\":600,\"x\":1682899200000,\"y\":600},{\"Fecha\":\"2023-06-01\",\"tipo\":\"VOZ TOTAL TRAFICO Outbound\",\"tráfico_voz\":321,\"x\":1685577600000,\"y\":321},{\"Fecha\":\"2023-07-01\",\"tipo\":\"VOZ TOTAL TRAFICO Outbound\",\"tráfico_voz\":599,\"x\":1688169600000,\"y\":599},{\"Fecha\":\"2023-08-01\",\"tipo\":\"VOZ TOTAL TRAFICO Outbound\",\"tráfico_voz\":623,\"x\":1690848000000,\"y\":623},{\"Fecha\":\"2023-09-01\",\"tipo\":\"VOZ TOTAL TRAFICO Outbound\",\"tráfico_voz\":625,\"x\":1693526400000,\"y\":625}],\"type\":\"line\"}],\"xAxis\":{\"type\":\"datetime\",\"title\":{\"text\":\"Fecha\"},\"categories\":null},\"subtitle\":{\"text\":\"Country: Ecuador\"},\"tooltip\":{\"shared\":true,\"formatter\":\"function(tooltip){\\n          function isArray(obj) {\\n          return Object.prototype.toString.call(obj) === '[object Array]';\\n          }\\n\\n          function splat(obj) {\\n          return isArray(obj) ? obj : [obj];\\n          }\\n\\n          var items = this.points || splat(this), series = items[0].series, s;\\n\\n          // sort the values\\n          items.sort(function(a, b){\\n          return ((a.y < b.y) ? -1 : ((a.y > b.y) ? 1 : 0));\\n          });\\n          items.reverse();\\n\\n          return tooltip.defaultFormatter.call(this, tooltip);\\n        }\",\"useHTML\":true,\"headerFormat\":\"<small>{point.key}<\\/small><table>\",\"pointFormat\":\"<tr><td style=\\\"color: {series.color}\\\">{series.name}: <\\/td><td style=\\\"text-align: right\\\"><b>{point.y}<\\/b><\\/td><\\/tr>\",\"footerFormat\":\"<\\/table>\"},\"caption\":{\"text\":\"Elaborated: Byron Raúl Avilés Rodríguez\"}},\"theme\":{\"colors\":[\"#2b908f\",\"#90ee7e\",\"#f45b5b\",\"#7798BF\",\"#aaeeee\",\"#ff0066\",\"#eeaaee\",\"#55BF3B\"],\"chart\":{\"backgroundColor\":{\"linearGradient\":{\"x1\":0,\"y1\":0,\"x2\":1,\"y2\":1},\"stops\":[[0,\"#2a2a2b\"],[1,\"#3e3e40\"]]},\"style\":{\"fontFamily\":\"Unica One, sans-serif\"},\"plotBorderColor\":\"#606063\"},\"title\":{\"style\":{\"color\":\"#E0E0E3\",\"textTransform\":\"uppercase\",\"fontSize\":\"20px\"}},\"subtitle\":{\"style\":{\"color\":\"#E0E0E3\",\"textTransform\":\"uppercase\"}},\"xAxis\":{\"gridLineColor\":\"#707073\",\"labels\":{\"style\":{\"color\":\"#E0E0E3\"}},\"lineColor\":\"#707073\",\"minorGridLineColor\":\"#505053\",\"tickColor\":\"#707073\",\"title\":{\"style\":{\"color\":\"#A0A0A3\"}}},\"yAxis\":{\"gridLineColor\":\"#707073\",\"labels\":{\"style\":{\"color\":\"#E0E0E3\"}},\"lineColor\":\"#707073\",\"minorGridLineColor\":\"#505053\",\"tickColor\":\"#707073\",\"tickWidth\":1,\"title\":{\"style\":{\"color\":\"#A0A0A3\"}}},\"tooltip\":{\"backgroundColor\":\"rgba(0, 0, 0, 0.85)\",\"style\":{\"color\":\"#F0F0F0\"}},\"plotOptions\":{\"series\":{\"dataLabels\":{\"color\":\"#B0B0B3\"},\"marker\":{\"lineColor\":\"#333\"}},\"boxplot\":{\"fillColor\":\"#505053\"},\"candlestick\":{\"lineColor\":\"white\"},\"errorbar\":{\"color\":\"white\"}},\"legend\":{\"itemStyle\":{\"color\":\"#E0E0E3\"},\"itemHoverStyle\":{\"color\":\"#FFF\"},\"itemHiddenStyle\":{\"color\":\"#606063\"}},\"credits\":{\"style\":{\"color\":\"#666\"}},\"labels\":{\"style\":{\"color\":\"#707073\"}},\"drilldown\":{\"activeAxisLabelStyle\":{\"color\":\"#F0F0F3\"},\"activeDataLabelStyle\":{\"color\":\"#F0F0F3\"}},\"navigation\":{\"buttonOptions\":{\"symbolStroke\":\"#DDDDDD\",\"theme\":{\"fill\":\"#505053\"}}},\"rangeSelector\":{\"buttonTheme\":{\"fill\":\"#505053\",\"stroke\":\"#000000\",\"style\":{\"color\":\"#CCC\"},\"states\":{\"hover\":{\"fill\":\"#707073\",\"stroke\":\"#000000\",\"style\":{\"color\":\"white\"}},\"select\":{\"fill\":\"#000003\",\"stroke\":\"#000000\",\"style\":{\"color\":\"white\"}}}},\"inputBoxBorderColor\":\"#505053\",\"inputStyle\":{\"backgroundColor\":\"#333\",\"color\":\"silver\"},\"labelStyle\":{\"color\":\"silver\"}},\"navigator\":{\"handles\":{\"backgroundColor\":\"#666\",\"borderColor\":\"#AAA\"},\"outlineColor\":\"#CCC\",\"maskFill\":\"rgba(255,255,255,0.1)\",\"series\":{\"color\":\"#7798BF\",\"lineColor\":\"#A6C7ED\"},\"xAxis\":{\"gridLineColor\":\"#505053\"}},\"scrollbar\":{\"barBackgroundColor\":\"#808083\",\"barBorderColor\":\"#808083\",\"buttonArrowColor\":\"#CCC\",\"buttonBackgroundColor\":\"#606063\",\"buttonBorderColor\":\"#606063\",\"rifleColor\":\"#FFF\",\"trackBackgroundColor\":\"#404043\",\"trackBorderColor\":\"#404043\"},\"legendBackgroundColor\":\"rgba(0, 0, 0, 0.5)\",\"background2\":\"#505053\",\"dataLabelsColor\":\"#B0B0B3\",\"textColor\":\"#C0C0C0\",\"contrastTextColor\":\"#F0F0F3\",\"maskColor\":\"rgba(255,255,255,0.3)\"},\"conf_opts\":{\"global\":{\"Date\":null,\"VMLRadialGradientURL\":\"http =//code.highcharts.com/list(version)/gfx/vml-radial-gradient.png\",\"canvasToolsURL\":\"http =//code.highcharts.com/list(version)/modules/canvas-tools.js\",\"getTimezoneOffset\":null,\"timezoneOffset\":0,\"useUTC\":true},\"lang\":{\"contextButtonTitle\":\"Chart context menu\",\"decimalPoint\":\".\",\"downloadCSV\":\"Download CSV\",\"downloadJPEG\":\"Download JPEG image\",\"downloadPDF\":\"Download PDF document\",\"downloadPNG\":\"Download PNG image\",\"downloadSVG\":\"Download SVG vector image\",\"downloadXLS\":\"Download XLS\",\"drillUpText\":\"◁ Back to {series.name}\",\"exitFullscreen\":\"Exit from full screen\",\"exportData\":{\"annotationHeader\":\"Annotations\",\"categoryDatetimeHeader\":\"DateTime\",\"categoryHeader\":\"Category\"},\"hideData\":\"Hide data table\",\"invalidDate\":null,\"loading\":\"Loading...\",\"months\":[\"January\",\"February\",\"March\",\"April\",\"May\",\"June\",\"July\",\"August\",\"September\",\"October\",\"November\",\"December\"],\"noData\":\"No data to display\",\"numericSymbolMagnitude\":1000,\"numericSymbols\":[\"k\",\"M\",\"G\",\"T\",\"P\",\"E\"],\"printChart\":\"Print chart\",\"resetZoom\":\"Reset zoom\",\"resetZoomTitle\":\"Reset zoom level 1:1\",\"shortMonths\":[\"Jan\",\"Feb\",\"Mar\",\"Apr\",\"May\",\"Jun\",\"Jul\",\"Aug\",\"Sep\",\"Oct\",\"Nov\",\"Dec\"],\"shortWeekdays\":[\"Sat\",\"Sun\",\"Mon\",\"Tue\",\"Wed\",\"Thu\",\"Fri\"],\"thousandsSep\":\" \",\"viewData\":\"View data table\",\"viewFullscreen\":\"View in full screen\",\"weekdays\":[\"Sunday\",\"Monday\",\"Tuesday\",\"Wednesday\",\"Thursday\",\"Friday\",\"Saturday\"]}},\"type\":\"chart\",\"fonts\":\"Unica+One\",\"debug\":false},\"evals\":[\"hc_opts.tooltip.formatter\"],\"jsHooks\":[]}</script>\n```\n:::\n\n::: {.cell-output-display}\n```{=html}\n<div class=\"highchart html-widget html-fill-item-overflow-hidden html-fill-item\" id=\"htmlwidget-36297adc5537cd8f9608\" style=\"width:100%;height:464px;\"></div>\n<script type=\"application/json\" data-for=\"htmlwidget-36297adc5537cd8f9608\">{\"x\":{\"hc_opts\":{\"chart\":{\"reflow\":true},\"title\":{\"text\":\"<b>Tráfico SMS Movistar Roaming Chile-Ecuador<\\/b>\"},\"yAxis\":{\"title\":{\"text\":\"tráfico_sms\"},\"type\":\"linear\"},\"credits\":{\"enabled\":false,\"enable\":true,\"text\":\"https://github.com/raulavilesrodriguez\"},\"exporting\":{\"enabled\":false},\"boost\":{\"enabled\":false},\"plotOptions\":{\"series\":{\"label\":{\"enabled\":false},\"turboThreshold\":0,\"showInLegend\":true},\"treemap\":{\"layoutAlgorithm\":\"squarified\"},\"scatter\":{\"marker\":{\"symbol\":\"circle\"}}},\"series\":[{\"name\":\"SMS TOTAL TRAFICO Inbound\",\"data\":[{\"Fecha\":\"2022-01-01\",\"tipo\":\"SMS TOTAL TRAFICO Inbound\",\"tráfico_sms\":1690,\"x\":1640995200000,\"y\":1690},{\"Fecha\":\"2022-02-01\",\"tipo\":\"SMS TOTAL TRAFICO Inbound\",\"tráfico_sms\":1113,\"x\":1643673600000,\"y\":1113},{\"Fecha\":\"2022-03-01\",\"tipo\":\"SMS TOTAL TRAFICO Inbound\",\"tráfico_sms\":2270,\"x\":1646092800000,\"y\":2270},{\"Fecha\":\"2022-04-01\",\"tipo\":\"SMS TOTAL TRAFICO Inbound\",\"tráfico_sms\":1859,\"x\":1648771200000,\"y\":1859},{\"Fecha\":\"2022-05-01\",\"tipo\":\"SMS TOTAL TRAFICO Inbound\",\"tráfico_sms\":2116,\"x\":1651363200000,\"y\":2116},{\"Fecha\":\"2022-06-01\",\"tipo\":\"SMS TOTAL TRAFICO Inbound\",\"tráfico_sms\":2197,\"x\":1654041600000,\"y\":2197},{\"Fecha\":\"2022-07-01\",\"tipo\":\"SMS TOTAL TRAFICO Inbound\",\"tráfico_sms\":2061,\"x\":1656633600000,\"y\":2061},{\"Fecha\":\"2022-08-01\",\"tipo\":\"SMS TOTAL TRAFICO Inbound\",\"tráfico_sms\":2300,\"x\":1659312000000,\"y\":2300},{\"Fecha\":\"2022-09-01\",\"tipo\":\"SMS TOTAL TRAFICO Inbound\",\"tráfico_sms\":1654,\"x\":1661990400000,\"y\":1654},{\"Fecha\":\"2022-10-01\",\"tipo\":\"SMS TOTAL TRAFICO Inbound\",\"tráfico_sms\":886,\"x\":1664582400000,\"y\":886},{\"Fecha\":\"2022-11-01\",\"tipo\":\"SMS TOTAL TRAFICO Inbound\",\"tráfico_sms\":769,\"x\":1667260800000,\"y\":769},{\"Fecha\":\"2022-12-01\",\"tipo\":\"SMS TOTAL TRAFICO Inbound\",\"tráfico_sms\":1321,\"x\":1669852800000,\"y\":1321},{\"Fecha\":\"2023-01-01\",\"tipo\":\"SMS TOTAL TRAFICO Inbound\",\"tráfico_sms\":1427,\"x\":1672531200000,\"y\":1427},{\"Fecha\":\"2023-02-01\",\"tipo\":\"SMS TOTAL TRAFICO Inbound\",\"tráfico_sms\":1451,\"x\":1675209600000,\"y\":1451},{\"Fecha\":\"2023-03-01\",\"tipo\":\"SMS TOTAL TRAFICO Inbound\",\"tráfico_sms\":1279,\"x\":1677628800000,\"y\":1279},{\"Fecha\":\"2023-04-01\",\"tipo\":\"SMS TOTAL TRAFICO Inbound\",\"tráfico_sms\":2652,\"x\":1680307200000,\"y\":2652},{\"Fecha\":\"2023-05-01\",\"tipo\":\"SMS TOTAL TRAFICO Inbound\",\"tráfico_sms\":1876,\"x\":1682899200000,\"y\":1876},{\"Fecha\":\"2023-06-01\",\"tipo\":\"SMS TOTAL TRAFICO Inbound\",\"tráfico_sms\":2203,\"x\":1685577600000,\"y\":2203},{\"Fecha\":\"2023-07-01\",\"tipo\":\"SMS TOTAL TRAFICO Inbound\",\"tráfico_sms\":2214,\"x\":1688169600000,\"y\":2214},{\"Fecha\":\"2023-08-01\",\"tipo\":\"SMS TOTAL TRAFICO Inbound\",\"tráfico_sms\":2896,\"x\":1690848000000,\"y\":2896},{\"Fecha\":\"2023-09-01\",\"tipo\":\"SMS TOTAL TRAFICO Inbound\",\"tráfico_sms\":2675,\"x\":1693526400000,\"y\":2675}],\"type\":\"line\"},{\"name\":\"SMS TOTAL TRAFICO Outbound\",\"data\":[{\"Fecha\":\"2022-01-01\",\"tipo\":\"SMS TOTAL TRAFICO Outbound\",\"tráfico_sms\":75,\"x\":1640995200000,\"y\":75},{\"Fecha\":\"2022-02-01\",\"tipo\":\"SMS TOTAL TRAFICO Outbound\",\"tráfico_sms\":50,\"x\":1643673600000,\"y\":50},{\"Fecha\":\"2022-03-01\",\"tipo\":\"SMS TOTAL TRAFICO Outbound\",\"tráfico_sms\":151,\"x\":1646092800000,\"y\":151},{\"Fecha\":\"2022-04-01\",\"tipo\":\"SMS TOTAL TRAFICO Outbound\",\"tráfico_sms\":229,\"x\":1648771200000,\"y\":229},{\"Fecha\":\"2022-05-01\",\"tipo\":\"SMS TOTAL TRAFICO Outbound\",\"tráfico_sms\":141,\"x\":1651363200000,\"y\":141},{\"Fecha\":\"2022-06-01\",\"tipo\":\"SMS TOTAL TRAFICO Outbound\",\"tráfico_sms\":142,\"x\":1654041600000,\"y\":142},{\"Fecha\":\"2022-07-01\",\"tipo\":\"SMS TOTAL TRAFICO Outbound\",\"tráfico_sms\":179,\"x\":1656633600000,\"y\":179},{\"Fecha\":\"2022-08-01\",\"tipo\":\"SMS TOTAL TRAFICO Outbound\",\"tráfico_sms\":225,\"x\":1659312000000,\"y\":225},{\"Fecha\":\"2022-09-01\",\"tipo\":\"SMS TOTAL TRAFICO Outbound\",\"tráfico_sms\":111,\"x\":1661990400000,\"y\":111},{\"Fecha\":\"2022-10-01\",\"tipo\":\"SMS TOTAL TRAFICO Outbound\",\"tráfico_sms\":209,\"x\":1664582400000,\"y\":209},{\"Fecha\":\"2022-11-01\",\"tipo\":\"SMS TOTAL TRAFICO Outbound\",\"tráfico_sms\":294,\"x\":1667260800000,\"y\":294},{\"Fecha\":\"2022-12-01\",\"tipo\":\"SMS TOTAL TRAFICO Outbound\",\"tráfico_sms\":281,\"x\":1669852800000,\"y\":281},{\"Fecha\":\"2023-01-01\",\"tipo\":\"SMS TOTAL TRAFICO Outbound\",\"tráfico_sms\":203,\"x\":1672531200000,\"y\":203},{\"Fecha\":\"2023-02-01\",\"tipo\":\"SMS TOTAL TRAFICO Outbound\",\"tráfico_sms\":122,\"x\":1675209600000,\"y\":122},{\"Fecha\":\"2023-03-01\",\"tipo\":\"SMS TOTAL TRAFICO Outbound\",\"tráfico_sms\":199,\"x\":1677628800000,\"y\":199},{\"Fecha\":\"2023-04-01\",\"tipo\":\"SMS TOTAL TRAFICO Outbound\",\"tráfico_sms\":337,\"x\":1680307200000,\"y\":337},{\"Fecha\":\"2023-05-01\",\"tipo\":\"SMS TOTAL TRAFICO Outbound\",\"tráfico_sms\":284,\"x\":1682899200000,\"y\":284},{\"Fecha\":\"2023-06-01\",\"tipo\":\"SMS TOTAL TRAFICO Outbound\",\"tráfico_sms\":230,\"x\":1685577600000,\"y\":230},{\"Fecha\":\"2023-07-01\",\"tipo\":\"SMS TOTAL TRAFICO Outbound\",\"tráfico_sms\":200,\"x\":1688169600000,\"y\":200},{\"Fecha\":\"2023-08-01\",\"tipo\":\"SMS TOTAL TRAFICO Outbound\",\"tráfico_sms\":228,\"x\":1690848000000,\"y\":228},{\"Fecha\":\"2023-09-01\",\"tipo\":\"SMS TOTAL TRAFICO Outbound\",\"tráfico_sms\":219,\"x\":1693526400000,\"y\":219}],\"type\":\"line\"}],\"xAxis\":{\"type\":\"datetime\",\"title\":{\"text\":\"Fecha\"},\"categories\":null},\"subtitle\":{\"text\":\"Country: Ecuador\"},\"tooltip\":{\"shared\":true,\"formatter\":\"function(tooltip){\\n          function isArray(obj) {\\n          return Object.prototype.toString.call(obj) === '[object Array]';\\n          }\\n\\n          function splat(obj) {\\n          return isArray(obj) ? obj : [obj];\\n          }\\n\\n          var items = this.points || splat(this), series = items[0].series, s;\\n\\n          // sort the values\\n          items.sort(function(a, b){\\n          return ((a.y < b.y) ? -1 : ((a.y > b.y) ? 1 : 0));\\n          });\\n          items.reverse();\\n\\n          return tooltip.defaultFormatter.call(this, tooltip);\\n        }\",\"useHTML\":true,\"headerFormat\":\"<small>{point.key}<\\/small><table>\",\"pointFormat\":\"<tr><td style=\\\"color: {series.color}\\\">{series.name}: <\\/td><td style=\\\"text-align: right\\\"><b>{point.y}<\\/b><\\/td><\\/tr>\",\"footerFormat\":\"<\\/table>\"},\"caption\":{\"text\":\"Elaborated: Byron Raúl Avilés Rodríguez\"}},\"theme\":{\"colors\":[\"#2b908f\",\"#90ee7e\",\"#f45b5b\",\"#7798BF\",\"#aaeeee\",\"#ff0066\",\"#eeaaee\",\"#55BF3B\"],\"chart\":{\"backgroundColor\":{\"linearGradient\":{\"x1\":0,\"y1\":0,\"x2\":1,\"y2\":1},\"stops\":[[0,\"#2a2a2b\"],[1,\"#3e3e40\"]]},\"style\":{\"fontFamily\":\"Unica One, sans-serif\"},\"plotBorderColor\":\"#606063\"},\"title\":{\"style\":{\"color\":\"#E0E0E3\",\"textTransform\":\"uppercase\",\"fontSize\":\"20px\"}},\"subtitle\":{\"style\":{\"color\":\"#E0E0E3\",\"textTransform\":\"uppercase\"}},\"xAxis\":{\"gridLineColor\":\"#707073\",\"labels\":{\"style\":{\"color\":\"#E0E0E3\"}},\"lineColor\":\"#707073\",\"minorGridLineColor\":\"#505053\",\"tickColor\":\"#707073\",\"title\":{\"style\":{\"color\":\"#A0A0A3\"}}},\"yAxis\":{\"gridLineColor\":\"#707073\",\"labels\":{\"style\":{\"color\":\"#E0E0E3\"}},\"lineColor\":\"#707073\",\"minorGridLineColor\":\"#505053\",\"tickColor\":\"#707073\",\"tickWidth\":1,\"title\":{\"style\":{\"color\":\"#A0A0A3\"}}},\"tooltip\":{\"backgroundColor\":\"rgba(0, 0, 0, 0.85)\",\"style\":{\"color\":\"#F0F0F0\"}},\"plotOptions\":{\"series\":{\"dataLabels\":{\"color\":\"#B0B0B3\"},\"marker\":{\"lineColor\":\"#333\"}},\"boxplot\":{\"fillColor\":\"#505053\"},\"candlestick\":{\"lineColor\":\"white\"},\"errorbar\":{\"color\":\"white\"}},\"legend\":{\"itemStyle\":{\"color\":\"#E0E0E3\"},\"itemHoverStyle\":{\"color\":\"#FFF\"},\"itemHiddenStyle\":{\"color\":\"#606063\"}},\"credits\":{\"style\":{\"color\":\"#666\"}},\"labels\":{\"style\":{\"color\":\"#707073\"}},\"drilldown\":{\"activeAxisLabelStyle\":{\"color\":\"#F0F0F3\"},\"activeDataLabelStyle\":{\"color\":\"#F0F0F3\"}},\"navigation\":{\"buttonOptions\":{\"symbolStroke\":\"#DDDDDD\",\"theme\":{\"fill\":\"#505053\"}}},\"rangeSelector\":{\"buttonTheme\":{\"fill\":\"#505053\",\"stroke\":\"#000000\",\"style\":{\"color\":\"#CCC\"},\"states\":{\"hover\":{\"fill\":\"#707073\",\"stroke\":\"#000000\",\"style\":{\"color\":\"white\"}},\"select\":{\"fill\":\"#000003\",\"stroke\":\"#000000\",\"style\":{\"color\":\"white\"}}}},\"inputBoxBorderColor\":\"#505053\",\"inputStyle\":{\"backgroundColor\":\"#333\",\"color\":\"silver\"},\"labelStyle\":{\"color\":\"silver\"}},\"navigator\":{\"handles\":{\"backgroundColor\":\"#666\",\"borderColor\":\"#AAA\"},\"outlineColor\":\"#CCC\",\"maskFill\":\"rgba(255,255,255,0.1)\",\"series\":{\"color\":\"#7798BF\",\"lineColor\":\"#A6C7ED\"},\"xAxis\":{\"gridLineColor\":\"#505053\"}},\"scrollbar\":{\"barBackgroundColor\":\"#808083\",\"barBorderColor\":\"#808083\",\"buttonArrowColor\":\"#CCC\",\"buttonBackgroundColor\":\"#606063\",\"buttonBorderColor\":\"#606063\",\"rifleColor\":\"#FFF\",\"trackBackgroundColor\":\"#404043\",\"trackBorderColor\":\"#404043\"},\"legendBackgroundColor\":\"rgba(0, 0, 0, 0.5)\",\"background2\":\"#505053\",\"dataLabelsColor\":\"#B0B0B3\",\"textColor\":\"#C0C0C0\",\"contrastTextColor\":\"#F0F0F3\",\"maskColor\":\"rgba(255,255,255,0.3)\"},\"conf_opts\":{\"global\":{\"Date\":null,\"VMLRadialGradientURL\":\"http =//code.highcharts.com/list(version)/gfx/vml-radial-gradient.png\",\"canvasToolsURL\":\"http =//code.highcharts.com/list(version)/modules/canvas-tools.js\",\"getTimezoneOffset\":null,\"timezoneOffset\":0,\"useUTC\":true},\"lang\":{\"contextButtonTitle\":\"Chart context menu\",\"decimalPoint\":\".\",\"downloadCSV\":\"Download CSV\",\"downloadJPEG\":\"Download JPEG image\",\"downloadPDF\":\"Download PDF document\",\"downloadPNG\":\"Download PNG image\",\"downloadSVG\":\"Download SVG vector image\",\"downloadXLS\":\"Download XLS\",\"drillUpText\":\"◁ Back to {series.name}\",\"exitFullscreen\":\"Exit from full screen\",\"exportData\":{\"annotationHeader\":\"Annotations\",\"categoryDatetimeHeader\":\"DateTime\",\"categoryHeader\":\"Category\"},\"hideData\":\"Hide data table\",\"invalidDate\":null,\"loading\":\"Loading...\",\"months\":[\"January\",\"February\",\"March\",\"April\",\"May\",\"June\",\"July\",\"August\",\"September\",\"October\",\"November\",\"December\"],\"noData\":\"No data to display\",\"numericSymbolMagnitude\":1000,\"numericSymbols\":[\"k\",\"M\",\"G\",\"T\",\"P\",\"E\"],\"printChart\":\"Print chart\",\"resetZoom\":\"Reset zoom\",\"resetZoomTitle\":\"Reset zoom level 1:1\",\"shortMonths\":[\"Jan\",\"Feb\",\"Mar\",\"Apr\",\"May\",\"Jun\",\"Jul\",\"Aug\",\"Sep\",\"Oct\",\"Nov\",\"Dec\"],\"shortWeekdays\":[\"Sat\",\"Sun\",\"Mon\",\"Tue\",\"Wed\",\"Thu\",\"Fri\"],\"thousandsSep\":\" \",\"viewData\":\"View data table\",\"viewFullscreen\":\"View in full screen\",\"weekdays\":[\"Sunday\",\"Monday\",\"Tuesday\",\"Wednesday\",\"Thursday\",\"Friday\",\"Saturday\"]}},\"type\":\"chart\",\"fonts\":\"Unica+One\",\"debug\":false},\"evals\":[\"hc_opts.tooltip.formatter\"],\"jsHooks\":[]}</script>\n```\n:::\n\n::: {.cell-output-display}\n```{=html}\n<div class=\"highchart html-widget html-fill-item-overflow-hidden html-fill-item\" id=\"htmlwidget-c918282c1cd9a7ce6e8a\" style=\"width:100%;height:464px;\"></div>\n<script type=\"application/json\" data-for=\"htmlwidget-c918282c1cd9a7ce6e8a\">{\"x\":{\"hc_opts\":{\"chart\":{\"reflow\":true},\"title\":{\"text\":\"<b>Tráfico Datos Movistar Roaming Chile-Ecuador<\\/b>\"},\"yAxis\":{\"title\":{\"text\":\"tráfico_datos\"},\"type\":\"linear\"},\"credits\":{\"enabled\":false,\"enable\":true,\"text\":\"https://github.com/raulavilesrodriguez\"},\"exporting\":{\"enabled\":false},\"boost\":{\"enabled\":false},\"plotOptions\":{\"series\":{\"label\":{\"enabled\":false},\"turboThreshold\":0,\"showInLegend\":true},\"treemap\":{\"layoutAlgorithm\":\"squarified\"},\"scatter\":{\"marker\":{\"symbol\":\"circle\"}}},\"series\":[{\"name\":\"DATOS TRAFICO Inbound (MB)\",\"data\":[{\"Fecha\":\"2022-01-01\",\"tipo\":\"DATOS TRAFICO Inbound (MB)\",\"tráfico_datos\":1482521,\"x\":1640995200000,\"y\":1482521},{\"Fecha\":\"2022-02-01\",\"tipo\":\"DATOS TRAFICO Inbound (MB)\",\"tráfico_datos\":1092797,\"x\":1643673600000,\"y\":1092797},{\"Fecha\":\"2022-03-01\",\"tipo\":\"DATOS TRAFICO Inbound (MB)\",\"tráfico_datos\":966309,\"x\":1646092800000,\"y\":966309},{\"Fecha\":\"2022-04-01\",\"tipo\":\"DATOS TRAFICO Inbound (MB)\",\"tráfico_datos\":863049,\"x\":1648771200000,\"y\":863049},{\"Fecha\":\"2022-05-01\",\"tipo\":\"DATOS TRAFICO Inbound (MB)\",\"tráfico_datos\":846161,\"x\":1651363200000,\"y\":846161},{\"Fecha\":\"2022-06-01\",\"tipo\":\"DATOS TRAFICO Inbound (MB)\",\"tráfico_datos\":997847,\"x\":1654041600000,\"y\":997847},{\"Fecha\":\"2022-07-01\",\"tipo\":\"DATOS TRAFICO Inbound (MB)\",\"tráfico_datos\":1092787,\"x\":1656633600000,\"y\":1092787},{\"Fecha\":\"2022-08-01\",\"tipo\":\"DATOS TRAFICO Inbound (MB)\",\"tráfico_datos\":1118983,\"x\":1659312000000,\"y\":1118983},{\"Fecha\":\"2022-09-01\",\"tipo\":\"DATOS TRAFICO Inbound (MB)\",\"tráfico_datos\":932013,\"x\":1661990400000,\"y\":932013},{\"Fecha\":\"2022-10-01\",\"tipo\":\"DATOS TRAFICO Inbound (MB)\",\"tráfico_datos\":1498177,\"x\":1664582400000,\"y\":1498177},{\"Fecha\":\"2022-11-01\",\"tipo\":\"DATOS TRAFICO Inbound (MB)\",\"tráfico_datos\":959919,\"x\":1667260800000,\"y\":959919},{\"Fecha\":\"2022-12-01\",\"tipo\":\"DATOS TRAFICO Inbound (MB)\",\"tráfico_datos\":1366101,\"x\":1669852800000,\"y\":1366101},{\"Fecha\":\"2023-01-01\",\"tipo\":\"DATOS TRAFICO Inbound (MB)\",\"tráfico_datos\":1857997,\"x\":1672531200000,\"y\":1857997},{\"Fecha\":\"2023-02-01\",\"tipo\":\"DATOS TRAFICO Inbound (MB)\",\"tráfico_datos\":1228254,\"x\":1675209600000,\"y\":1228254},{\"Fecha\":\"2023-03-01\",\"tipo\":\"DATOS TRAFICO Inbound (MB)\",\"tráfico_datos\":1460344,\"x\":1677628800000,\"y\":1460344},{\"Fecha\":\"2023-04-01\",\"tipo\":\"DATOS TRAFICO Inbound (MB)\",\"tráfico_datos\":1585164,\"x\":1680307200000,\"y\":1585164},{\"Fecha\":\"2023-05-01\",\"tipo\":\"DATOS TRAFICO Inbound (MB)\",\"tráfico_datos\":1218827,\"x\":1682899200000,\"y\":1218827},{\"Fecha\":\"2023-06-01\",\"tipo\":\"DATOS TRAFICO Inbound (MB)\",\"tráfico_datos\":1224717,\"x\":1685577600000,\"y\":1224717},{\"Fecha\":\"2023-07-01\",\"tipo\":\"DATOS TRAFICO Inbound (MB)\",\"tráfico_datos\":1567770,\"x\":1688169600000,\"y\":1567770},{\"Fecha\":\"2023-08-01\",\"tipo\":\"DATOS TRAFICO Inbound (MB)\",\"tráfico_datos\":1521745,\"x\":1690848000000,\"y\":1521745},{\"Fecha\":\"2023-09-01\",\"tipo\":\"DATOS TRAFICO Inbound (MB)\",\"tráfico_datos\":1244030,\"x\":1693526400000,\"y\":1244030}],\"type\":\"line\"},{\"name\":\"DATOS TRAFICO Outbound (MB)\",\"data\":[{\"Fecha\":\"2022-01-01\",\"tipo\":\"DATOS TRAFICO Outbound (MB)\",\"tráfico_datos\":221778,\"x\":1640995200000,\"y\":221778},{\"Fecha\":\"2022-02-01\",\"tipo\":\"DATOS TRAFICO Outbound (MB)\",\"tráfico_datos\":215806,\"x\":1643673600000,\"y\":215806},{\"Fecha\":\"2022-03-01\",\"tipo\":\"DATOS TRAFICO Outbound (MB)\",\"tráfico_datos\":268276,\"x\":1646092800000,\"y\":268276},{\"Fecha\":\"2022-04-01\",\"tipo\":\"DATOS TRAFICO Outbound (MB)\",\"tráfico_datos\":376732,\"x\":1648771200000,\"y\":376732},{\"Fecha\":\"2022-05-01\",\"tipo\":\"DATOS TRAFICO Outbound (MB)\",\"tráfico_datos\":318689,\"x\":1651363200000,\"y\":318689},{\"Fecha\":\"2022-06-01\",\"tipo\":\"DATOS TRAFICO Outbound (MB)\",\"tráfico_datos\":384785,\"x\":1654041600000,\"y\":384785},{\"Fecha\":\"2022-07-01\",\"tipo\":\"DATOS TRAFICO Outbound (MB)\",\"tráfico_datos\":342173,\"x\":1656633600000,\"y\":342173},{\"Fecha\":\"2022-08-01\",\"tipo\":\"DATOS TRAFICO Outbound (MB)\",\"tráfico_datos\":562244,\"x\":1659312000000,\"y\":562244},{\"Fecha\":\"2022-09-01\",\"tipo\":\"DATOS TRAFICO Outbound (MB)\",\"tráfico_datos\":168856,\"x\":1661990400000,\"y\":168856},{\"Fecha\":\"2022-10-01\",\"tipo\":\"DATOS TRAFICO Outbound (MB)\",\"tráfico_datos\":498689,\"x\":1664582400000,\"y\":498689},{\"Fecha\":\"2022-11-01\",\"tipo\":\"DATOS TRAFICO Outbound (MB)\",\"tráfico_datos\":585417,\"x\":1667260800000,\"y\":585417},{\"Fecha\":\"2022-12-01\",\"tipo\":\"DATOS TRAFICO Outbound (MB)\",\"tráfico_datos\":710722,\"x\":1669852800000,\"y\":710722},{\"Fecha\":\"2023-01-01\",\"tipo\":\"DATOS TRAFICO Outbound (MB)\",\"tráfico_datos\":464480,\"x\":1672531200000,\"y\":464480},{\"Fecha\":\"2023-02-01\",\"tipo\":\"DATOS TRAFICO Outbound (MB)\",\"tráfico_datos\":480059,\"x\":1675209600000,\"y\":480059},{\"Fecha\":\"2023-03-01\",\"tipo\":\"DATOS TRAFICO Outbound (MB)\",\"tráfico_datos\":644900,\"x\":1677628800000,\"y\":644900},{\"Fecha\":\"2023-04-01\",\"tipo\":\"DATOS TRAFICO Outbound (MB)\",\"tráfico_datos\":646978,\"x\":1680307200000,\"y\":646978},{\"Fecha\":\"2023-05-01\",\"tipo\":\"DATOS TRAFICO Outbound (MB)\",\"tráfico_datos\":720920,\"x\":1682899200000,\"y\":720920},{\"Fecha\":\"2023-06-01\",\"tipo\":\"DATOS TRAFICO Outbound (MB)\",\"tráfico_datos\":450863,\"x\":1685577600000,\"y\":450863},{\"Fecha\":\"2023-07-01\",\"tipo\":\"DATOS TRAFICO Outbound (MB)\",\"tráfico_datos\":623719,\"x\":1688169600000,\"y\":623719},{\"Fecha\":\"2023-08-01\",\"tipo\":\"DATOS TRAFICO Outbound (MB)\",\"tráfico_datos\":809488,\"x\":1690848000000,\"y\":809488},{\"Fecha\":\"2023-09-01\",\"tipo\":\"DATOS TRAFICO Outbound (MB)\",\"tráfico_datos\":648306,\"x\":1693526400000,\"y\":648306}],\"type\":\"line\"}],\"xAxis\":{\"type\":\"datetime\",\"title\":{\"text\":\"Fecha\"},\"categories\":null},\"subtitle\":{\"text\":\"Country: Ecuador\"},\"tooltip\":{\"shared\":true,\"formatter\":\"function(tooltip){\\n          function isArray(obj) {\\n          return Object.prototype.toString.call(obj) === '[object Array]';\\n          }\\n\\n          function splat(obj) {\\n          return isArray(obj) ? obj : [obj];\\n          }\\n\\n          var items = this.points || splat(this), series = items[0].series, s;\\n\\n          // sort the values\\n          items.sort(function(a, b){\\n          return ((a.y < b.y) ? -1 : ((a.y > b.y) ? 1 : 0));\\n          });\\n          items.reverse();\\n\\n          return tooltip.defaultFormatter.call(this, tooltip);\\n        }\",\"useHTML\":true,\"headerFormat\":\"<small>{point.key}<\\/small><table>\",\"pointFormat\":\"<tr><td style=\\\"color: {series.color}\\\">{series.name}: <\\/td><td style=\\\"text-align: right\\\"><b>{point.y}<\\/b><\\/td><\\/tr>\",\"footerFormat\":\"<\\/table>\"},\"caption\":{\"text\":\"Elaborated: Byron Raúl Avilés Rodríguez\"}},\"theme\":{\"colors\":[\"#2b908f\",\"#90ee7e\",\"#f45b5b\",\"#7798BF\",\"#aaeeee\",\"#ff0066\",\"#eeaaee\",\"#55BF3B\"],\"chart\":{\"backgroundColor\":{\"linearGradient\":{\"x1\":0,\"y1\":0,\"x2\":1,\"y2\":1},\"stops\":[[0,\"#2a2a2b\"],[1,\"#3e3e40\"]]},\"style\":{\"fontFamily\":\"Unica One, sans-serif\"},\"plotBorderColor\":\"#606063\"},\"title\":{\"style\":{\"color\":\"#E0E0E3\",\"textTransform\":\"uppercase\",\"fontSize\":\"20px\"}},\"subtitle\":{\"style\":{\"color\":\"#E0E0E3\",\"textTransform\":\"uppercase\"}},\"xAxis\":{\"gridLineColor\":\"#707073\",\"labels\":{\"style\":{\"color\":\"#E0E0E3\"}},\"lineColor\":\"#707073\",\"minorGridLineColor\":\"#505053\",\"tickColor\":\"#707073\",\"title\":{\"style\":{\"color\":\"#A0A0A3\"}}},\"yAxis\":{\"gridLineColor\":\"#707073\",\"labels\":{\"style\":{\"color\":\"#E0E0E3\"}},\"lineColor\":\"#707073\",\"minorGridLineColor\":\"#505053\",\"tickColor\":\"#707073\",\"tickWidth\":1,\"title\":{\"style\":{\"color\":\"#A0A0A3\"}}},\"tooltip\":{\"backgroundColor\":\"rgba(0, 0, 0, 0.85)\",\"style\":{\"color\":\"#F0F0F0\"}},\"plotOptions\":{\"series\":{\"dataLabels\":{\"color\":\"#B0B0B3\"},\"marker\":{\"lineColor\":\"#333\"}},\"boxplot\":{\"fillColor\":\"#505053\"},\"candlestick\":{\"lineColor\":\"white\"},\"errorbar\":{\"color\":\"white\"}},\"legend\":{\"itemStyle\":{\"color\":\"#E0E0E3\"},\"itemHoverStyle\":{\"color\":\"#FFF\"},\"itemHiddenStyle\":{\"color\":\"#606063\"}},\"credits\":{\"style\":{\"color\":\"#666\"}},\"labels\":{\"style\":{\"color\":\"#707073\"}},\"drilldown\":{\"activeAxisLabelStyle\":{\"color\":\"#F0F0F3\"},\"activeDataLabelStyle\":{\"color\":\"#F0F0F3\"}},\"navigation\":{\"buttonOptions\":{\"symbolStroke\":\"#DDDDDD\",\"theme\":{\"fill\":\"#505053\"}}},\"rangeSelector\":{\"buttonTheme\":{\"fill\":\"#505053\",\"stroke\":\"#000000\",\"style\":{\"color\":\"#CCC\"},\"states\":{\"hover\":{\"fill\":\"#707073\",\"stroke\":\"#000000\",\"style\":{\"color\":\"white\"}},\"select\":{\"fill\":\"#000003\",\"stroke\":\"#000000\",\"style\":{\"color\":\"white\"}}}},\"inputBoxBorderColor\":\"#505053\",\"inputStyle\":{\"backgroundColor\":\"#333\",\"color\":\"silver\"},\"labelStyle\":{\"color\":\"silver\"}},\"navigator\":{\"handles\":{\"backgroundColor\":\"#666\",\"borderColor\":\"#AAA\"},\"outlineColor\":\"#CCC\",\"maskFill\":\"rgba(255,255,255,0.1)\",\"series\":{\"color\":\"#7798BF\",\"lineColor\":\"#A6C7ED\"},\"xAxis\":{\"gridLineColor\":\"#505053\"}},\"scrollbar\":{\"barBackgroundColor\":\"#808083\",\"barBorderColor\":\"#808083\",\"buttonArrowColor\":\"#CCC\",\"buttonBackgroundColor\":\"#606063\",\"buttonBorderColor\":\"#606063\",\"rifleColor\":\"#FFF\",\"trackBackgroundColor\":\"#404043\",\"trackBorderColor\":\"#404043\"},\"legendBackgroundColor\":\"rgba(0, 0, 0, 0.5)\",\"background2\":\"#505053\",\"dataLabelsColor\":\"#B0B0B3\",\"textColor\":\"#C0C0C0\",\"contrastTextColor\":\"#F0F0F3\",\"maskColor\":\"rgba(255,255,255,0.3)\"},\"conf_opts\":{\"global\":{\"Date\":null,\"VMLRadialGradientURL\":\"http =//code.highcharts.com/list(version)/gfx/vml-radial-gradient.png\",\"canvasToolsURL\":\"http =//code.highcharts.com/list(version)/modules/canvas-tools.js\",\"getTimezoneOffset\":null,\"timezoneOffset\":0,\"useUTC\":true},\"lang\":{\"contextButtonTitle\":\"Chart context menu\",\"decimalPoint\":\".\",\"downloadCSV\":\"Download CSV\",\"downloadJPEG\":\"Download JPEG image\",\"downloadPDF\":\"Download PDF document\",\"downloadPNG\":\"Download PNG image\",\"downloadSVG\":\"Download SVG vector image\",\"downloadXLS\":\"Download XLS\",\"drillUpText\":\"◁ Back to {series.name}\",\"exitFullscreen\":\"Exit from full screen\",\"exportData\":{\"annotationHeader\":\"Annotations\",\"categoryDatetimeHeader\":\"DateTime\",\"categoryHeader\":\"Category\"},\"hideData\":\"Hide data table\",\"invalidDate\":null,\"loading\":\"Loading...\",\"months\":[\"January\",\"February\",\"March\",\"April\",\"May\",\"June\",\"July\",\"August\",\"September\",\"October\",\"November\",\"December\"],\"noData\":\"No data to display\",\"numericSymbolMagnitude\":1000,\"numericSymbols\":[\"k\",\"M\",\"G\",\"T\",\"P\",\"E\"],\"printChart\":\"Print chart\",\"resetZoom\":\"Reset zoom\",\"resetZoomTitle\":\"Reset zoom level 1:1\",\"shortMonths\":[\"Jan\",\"Feb\",\"Mar\",\"Apr\",\"May\",\"Jun\",\"Jul\",\"Aug\",\"Sep\",\"Oct\",\"Nov\",\"Dec\"],\"shortWeekdays\":[\"Sat\",\"Sun\",\"Mon\",\"Tue\",\"Wed\",\"Thu\",\"Fri\"],\"thousandsSep\":\" \",\"viewData\":\"View data table\",\"viewFullscreen\":\"View in full screen\",\"weekdays\":[\"Sunday\",\"Monday\",\"Tuesday\",\"Wednesday\",\"Thursday\",\"Friday\",\"Saturday\"]}},\"type\":\"chart\",\"fonts\":\"Unica+One\",\"debug\":false},\"evals\":[\"hc_opts.tooltip.formatter\"],\"jsHooks\":[]}</script>\n```\n:::\n:::\n\n<br>\n**Conclusión**.- Movistar en el mercado mayorista del servicio de roaming interncional con las operadoras de Chile, obtuvo beneficios económicos en el periodo analizado (enero 2022 - septiembre 2023), debido a que la relación de tráfico Inbound versus el tráfico Outbound de los servicios de voz, sms y datos es mayor a 1.\n",
    "supporting": [],
    "filters": [
      "rmarkdown/pagebreak.lua"
    ],
    "includes": {
      "include-in-header": [
        "<script src=\"site_libs/htmlwidgets-1.6.2/htmlwidgets.js\"></script>\r\n<link href=\"site_libs/datatables-css-0.0.0/datatables-crosstalk.css\" rel=\"stylesheet\" />\r\n<script src=\"site_libs/datatables-binding-0.28/datatables.js\"></script>\r\n<script src=\"site_libs/jquery-3.6.0/jquery-3.6.0.min.js\"></script>\r\n<link href=\"site_libs/dt-core-1.13.4/css/jquery.dataTables.min.css\" rel=\"stylesheet\" />\r\n<link href=\"site_libs/dt-core-1.13.4/css/jquery.dataTables.extra.css\" rel=\"stylesheet\" />\r\n<script src=\"site_libs/dt-core-1.13.4/js/jquery.dataTables.min.js\"></script>\r\n<link href=\"site_libs/crosstalk-1.2.0/css/crosstalk.min.css\" rel=\"stylesheet\" />\r\n<script src=\"site_libs/crosstalk-1.2.0/js/crosstalk.min.js\"></script>\r\n<script src=\"site_libs/proj4js-2.3.15/proj4.js\"></script>\r\n<link href=\"site_libs/highcharts-9.3.1/css/motion.css\" rel=\"stylesheet\" />\r\n<script src=\"site_libs/highcharts-9.3.1/highcharts.js\"></script>\r\n<script src=\"site_libs/highcharts-9.3.1/highcharts-3d.js\"></script>\r\n<script src=\"site_libs/highcharts-9.3.1/highcharts-more.js\"></script>\r\n<script src=\"site_libs/highcharts-9.3.1/modules/stock.js\"></script>\r\n<script src=\"site_libs/highcharts-9.3.1/modules/map.js\"></script>\r\n<script src=\"site_libs/highcharts-9.3.1/modules/data.js\"></script>\r\n<script src=\"site_libs/highcharts-9.3.1/modules/exporting.js\"></script>\r\n<script src=\"site_libs/highcharts-9.3.1/modules/offline-exporting.js\"></script>\r\n<script src=\"site_libs/highcharts-9.3.1/modules/drilldown.js\"></script>\r\n<script src=\"site_libs/highcharts-9.3.1/modules/item-series.js\"></script>\r\n<script src=\"site_libs/highcharts-9.3.1/modules/overlapping-datalabels.js\"></script>\r\n<script src=\"site_libs/highcharts-9.3.1/modules/annotations.js\"></script>\r\n<script src=\"site_libs/highcharts-9.3.1/modules/export-data.js\"></script>\r\n<script src=\"site_libs/highcharts-9.3.1/modules/funnel.js\"></script>\r\n<script src=\"site_libs/highcharts-9.3.1/modules/heatmap.js\"></script>\r\n<script src=\"site_libs/highcharts-9.3.1/modules/treemap.js\"></script>\r\n<script src=\"site_libs/highcharts-9.3.1/modules/sankey.js\"></script>\r\n<script src=\"site_libs/highcharts-9.3.1/modules/dependency-wheel.js\"></script>\r\n<script src=\"site_libs/highcharts-9.3.1/modules/organization.js\"></script>\r\n<script src=\"site_libs/highcharts-9.3.1/modules/solid-gauge.js\"></script>\r\n<script src=\"site_libs/highcharts-9.3.1/modules/streamgraph.js\"></script>\r\n<script src=\"site_libs/highcharts-9.3.1/modules/sunburst.js\"></script>\r\n<script src=\"site_libs/highcharts-9.3.1/modules/vector.js\"></script>\r\n<script src=\"site_libs/highcharts-9.3.1/modules/wordcloud.js\"></script>\r\n<script src=\"site_libs/highcharts-9.3.1/modules/xrange.js\"></script>\r\n<script src=\"site_libs/highcharts-9.3.1/modules/tilemap.js\"></script>\r\n<script src=\"site_libs/highcharts-9.3.1/modules/venn.js\"></script>\r\n<script src=\"site_libs/highcharts-9.3.1/modules/gantt.js\"></script>\r\n<script src=\"site_libs/highcharts-9.3.1/modules/timeline.js\"></script>\r\n<script src=\"site_libs/highcharts-9.3.1/modules/parallel-coordinates.js\"></script>\r\n<script src=\"site_libs/highcharts-9.3.1/modules/bullet.js\"></script>\r\n<script src=\"site_libs/highcharts-9.3.1/modules/coloraxis.js\"></script>\r\n<script src=\"site_libs/highcharts-9.3.1/modules/dumbbell.js\"></script>\r\n<script src=\"site_libs/highcharts-9.3.1/modules/lollipop.js\"></script>\r\n<script src=\"site_libs/highcharts-9.3.1/modules/series-label.js\"></script>\r\n<script src=\"site_libs/highcharts-9.3.1/plugins/motion.js\"></script>\r\n<script src=\"site_libs/highcharts-9.3.1/custom/reset.js\"></script>\r\n<script src=\"site_libs/highcharts-9.3.1/modules/boost.js\"></script>\r\n<script src=\"site_libs/highchart-binding-0.9.4/highchart.js\"></script>\r\n"
      ]
    },
    "engineDependencies": {},
    "preserve": {},
    "postProcess": true
  }
}